vkwave_api/__init__.py
vkwave_api-0.3.5.dist-info/WHEEL
vkwave_api-0.3.5.dist-info/METADATA
vkwave_api-0.3.5.dist-info/RECORD
