Metadata-Version: 2.1
Name: vkwave-api
Version: 0.3.5
Summary: Accessing VK API for humans.
License: MIT
Author: prostomarkeloff
Author-email: 28061158+prostomarkeloff@users.noreply.github.com
Requires-Python: >=3.7,<4.0
Classifier: License :: OSI Approved :: MIT License
Classifier: Programming Language :: Python :: 3
Classifier: Programming Language :: Python :: 3.7
Classifier: Programming Language :: Python :: 3.8
Classifier: Programming Language :: Python :: 3.9
Requires-Dist: vkwave
